chorm/__init__.py
chorm/_context_managers.py
chorm/async_engine.py
chorm/async_pool.py
chorm/async_session.py
chorm/auto_migration.py
chorm/batch.py
chorm/batch_optimized.py
chorm/cli.py
chorm/codecs.py
chorm/ddl.py
chorm/declarative.py
chorm/engine.py
chorm/exceptions.py
chorm/health.py
chorm/introspection.py
chorm/metadata.py
chorm/metrics.py
chorm/migration.py
chorm/pool.py
chorm/profiler.py
chorm/query_cache.py
chorm/query_settings.py
chorm/result.py
chorm/retry.py
chorm/session.py
chorm/table_engines.py
chorm/types.py
chorm/utils.py
chorm/validators.py
chorm/sql/__init__.py
chorm/sql/compiler.py
chorm/sql/ddl.py
chorm/sql/dml.py
chorm/sql/explain.py
chorm/sql/expression.py
chorm/sql/selectable.py
clickhouse_chorm-0.2.3.dist-info/METADATA
clickhouse_chorm-0.2.3.dist-info/WHEEL
clickhouse_chorm-0.2.3.dist-info/entry_points.txt
clickhouse_chorm-0.2.3.dist-info/licenses/LICENSE
clickhouse_chorm-0.2.3.dist-info/RECORD
