Metadata-Version: 2.4
Name: clickhouse-chorm
Version: 0.2.3
Summary: A modern, type-safe ORM for ClickHouse with full support for ClickHouse-specific features
Project-URL: Homepage, https://github.com/zwickvitaly/chorm
Project-URL: Repository, https://github.com/zwickvitaly/chorm
Project-URL: Issues, https://github.com/zwickvitaly/chorm/issues
Project-URL: Changelog, https://github.com/zwickvitaly/chorm/blob/main/CHANGELOG.md
Project-URL: Documentation, https://github.com/zwickvitaly/chorm#readme
Author-email: Vitaly Zwick <zwickvitaly@gmail.com>
License: MIT
License-File: LICENSE
Keywords: analytics,async,clickhouse,data-warehouse,database,mergetree,olap,orm,query-builder,sql
Classifier: Development Status :: 4 - Beta
Classifier: Framework :: AsyncIO
Classifier: Intended Audience :: Developers
Classifier: License :: OSI Approved :: MIT License
Classifier: Operating System :: OS Independent
Classifier: Programming Language :: Python :: 3
Classifier: Programming Language :: Python :: 3 :: Only
Classifier: Programming Language :: Python :: 3.12
Classifier: Programming Language :: Python :: 3.13
Classifier: Topic :: Database
Classifier: Topic :: Database :: Front-Ends
Classifier: Topic :: Software Development :: Libraries :: Python Modules
Classifier: Typing :: Typed
Requires-Python: >=3.12
Requires-Dist: clickhouse-connect>=0.9.2
Provides-Extra: dev
Requires-Dist: black>=25.9.0; extra == 'dev'
Requires-Dist: pytest-asyncio>=1.3.0; extra == 'dev'
Requires-Dist: pytest>=8.4.2; extra == 'dev'
Provides-Extra: pandas
Requires-Dist: pandas>=2.3.3; extra == 'pandas'
